README.md
setup.py
bin/stub
spudtr/__init__.py
spudtr/epf.py
spudtr/epochs_plots.py
spudtr/fake_epochs_data.py
spudtr/filters.py
spudtr/mneutils.py
spudtr.egg-info/PKG-INFO
spudtr.egg-info/SOURCES.txt
spudtr.egg-info/dependency_links.txt
spudtr.egg-info/top_level.txt
spudtr/resources/mne_32chan_xyz.yml
spudtr/resources/mne_32chan_xyz_spherical.yml
spudtr/resources/p3_feather.yml