Metadata-Version: 2.1
Name: spudtr
Version: 0.0.17
Summary: some pandas utility dataframe transforms
Home-page: https://github.com/kutaslab/spudtr
Author: Thomas P. Urbach
Author-email: turbach@ucsd.edu
License: UNKNOWN
Platform: UNKNOWN
Classifier: Programming Language :: Python :: 3
Classifier: License :: OSI Approved :: BSD License
Classifier: Intended Audience :: Science/Research
